typedhttp/__init__.py
typedhttp/exc.py
typedhttp/main.py
typedhttp/py.typed
typedhttp/requests_hook.py
typedhttp-0.4.0.dist-info/METADATA
typedhttp-0.4.0.dist-info/WHEEL
typedhttp-0.4.0.dist-info/RECORD
