Metadata-Version: 2.1
Name: typedhttp
Version: 0.4.0
Summary: 
Author: Lucas Silva
Author-email: lucas76leonardo@gmail.com
Requires-Python: >=3.8,<4.0
Classifier: Programming Language :: Python :: 3
Classifier: Programming Language :: Python :: 3.8
Classifier: Programming Language :: Python :: 3.9
Classifier: Programming Language :: Python :: 3.10
Classifier: Programming Language :: Python :: 3.11
Requires-Dist: requests[requests] (>=2.31.0,<3.0.0)
